a2y_cv.cp312-win_amd64.pyd
a2y_cv-1.0.3.dist-info/licenses/LICENSE
a2y_cv-1.0.3.dist-info/METADATA
a2y_cv-1.0.3.dist-info/WHEEL
a2y_cv-1.0.3.dist-info/top_level.txt
a2y_cv-1.0.3.dist-info/RECORD
